CHANGES.rst
CONTRIBUTORS.rst
MANIFEST.in
README.rst
bootstrap.py
buildout.cfg
setup.py
cpskin/__init__.py
cpskin.diazotheme.smart.egg-info/PKG-INFO
cpskin.diazotheme.smart.egg-info/SOURCES.txt
cpskin.diazotheme.smart.egg-info/dependency_links.txt
cpskin.diazotheme.smart.egg-info/entry_points.txt
cpskin.diazotheme.smart.egg-info/namespace_packages.txt
cpskin.diazotheme.smart.egg-info/not-zip-safe
cpskin.diazotheme.smart.egg-info/requires.txt
cpskin.diazotheme.smart.egg-info/top_level.txt
cpskin/diazotheme/__init__.py
cpskin/diazotheme/smart/__init__.py
cpskin/diazotheme/smart/configure.zcml
cpskin/diazotheme/smart/upgradehandlers.py
cpskin/diazotheme/smart/profiles/default/cssregistry.xml
cpskin/diazotheme/smart/profiles/default/jsregistry.xml
cpskin/diazotheme/smart/profiles/default/lessregistry.xml
cpskin/diazotheme/smart/profiles/default/metadata.xml
cpskin/diazotheme/smart/profiles/default/theme.xml
cpskin/diazotheme/smart/profiles/uninstall/cssregistry.xml
cpskin/diazotheme/smart/profiles/uninstall/jsregistry.xml
cpskin/diazotheme/smart/profiles/uninstall/lessregistry.xml
cpskin/diazotheme/smart/static/manifest.cfg
cpskin/diazotheme/smart/static/preview.png
cpskin/diazotheme/smart/static/rules.xml
cpskin/diazotheme/smart/static/css/styles.css
cpskin/diazotheme/smart/static/images/cd-top-arrow.svg
cpskin/diazotheme/smart/static/images/date.jpg
cpskin/diazotheme/smart/static/images/footer-map.jpg
cpskin/diazotheme/smart/static/images/organization-picto.jpg
cpskin/diazotheme/smart/static/images/personne-picto.jpg
cpskin/diazotheme/smart/static/js/cpskin_smart.js
cpskin/diazotheme/smart/static/js/sticky-navigation.js
cpskin/diazotheme/smart/static/less/mobile.less
cpskin/diazotheme/smart/static/less/mobilelarge.less
cpskin/diazotheme/smart/static/less/namur.less
cpskin/diazotheme/smart/static/less/printnamur.less
cpskin/diazotheme/smart/static/less/styles.less
cpskin/diazotheme/smart/static/less/variables.less
cpskin/diazotheme/smart/static/rules/footer.xml
cpskin/diazotheme/smart/static/rules/header.xml
cpskin/diazotheme/smart/static/rules/structures.xml
docs/LICENSE.GPL
docs/LICENSE.rst