Metadata-Version: 1.1
Name: cpskin.diazotheme.smart
Version: 0.6.29
Summary: Smart theme for CPSKin
Home-page: https://github.com/IMIO/cpskin.diazotheme.smart/
Author: IMIO
Author-email: support@imio.be
License: GPL
Keywords: imio cpskin theme
Platform: UNKNOWN
Classifier: Environment :: Web Environment
Classifier: Framework :: Plone
Classifier: Framework :: Plone :: 4.3
Classifier: Programming Language :: Python
Classifier: Programming Language :: Python :: 2.7
